tambus/__init__.py
tambus/components.py
tambus/engine.py
tambus/mdengine.py
tambus-1.0.0.dist-info/LICENSE
tambus-1.0.0.dist-info/METADATA
tambus-1.0.0.dist-info/WHEEL
tambus-1.0.0.dist-info/top_level.txt
tambus-1.0.0.dist-info/RECORD
