Metadata-Version: 2.1
Name: tambus
Version: 1.0.0
Summary: Bambus Template Engine
Home-page: https://github.com/somespi/tambus
Author: Someone.
Author-email: someonegithub@gmail.com
Classifier: Programming Language :: Python :: 3
Classifier: License :: OSI Approved :: MIT License
Classifier: Operating System :: OS Independent
License-File: LICENSE
